smartpath/__init__.py
smartpath/php/getsecs.php
smartpath-0.14.dist-info/LICENSE
smartpath-0.14.dist-info/METADATA
smartpath-0.14.dist-info/WHEEL
smartpath-0.14.dist-info/top_level.txt
smartpath-0.14.dist-info/RECORD
