Metadata-Version: 2.1
Name: smartpath
Version: 0.14
Summary: smartpath implements the SmartFileSystem class (and connector classes) to provide unified object-oriented access to filesystems of various protocols.  It draws a number of parallels to the Windows FileSystemObject
Home-page: http://github.com/miking7/smartpath
Author: Michael Engelbrecht
Author-email: michaelndani@gmail.com
License: MIT
Platform: UNKNOWN
Requires-Python: ==2.7.*
